trt_cloud/ENGINE_LICENSE.txt
trt_cloud/LICENSE.txt
trt_cloud/__init__.py
trt_cloud/api/__init__.py
trt_cloud/api/orchestrator.py
trt_cloud/build_spec/__init__.py
trt_cloud/build_spec/build_input_source.py
trt_cloud/build_spec/build_options.py
trt_cloud/build_spec/build_recipe.py
trt_cloud/cli.py
trt_cloud/client.py
trt_cloud/constants.py
trt_cloud/ngc_registry.py
trt_cloud/ngc_utils.py
trt_cloud/polygraphy_helper.py
trt_cloud/refitter/__init__.py
trt_cloud/refitter/refit_helper.py
trt_cloud/rest_endpoints.py
trt_cloud/state.py
trt_cloud/subcommands/__init__.py
trt_cloud/subcommands/base_subcommand.py
trt_cloud/subcommands/build.py
trt_cloud/subcommands/catalog.py
trt_cloud/subcommands/credits.py
trt_cloud/subcommands/info.py
trt_cloud/subcommands/login.py
trt_cloud/subcommands/refit.py
trt_cloud/subcommands/sweep.py
trt_cloud/subcommands/utils.py
trt_cloud/sweeper.py
trt_cloud/trtllm_helper.py
trt_cloud/types.py
trt_cloud/utils.py
trt_cloud/versions.py
trt_cloud-0.6.1.dist-info/METADATA
trt_cloud-0.6.1.dist-info/WHEEL
trt_cloud-0.6.1.dist-info/entry_points.txt
trt_cloud-0.6.1.dist-info/RECORD
